<?xml version="1.1" encoding="UTF-8" standalone="no"?>
<databaseChangeLog
    xmlns="http://www.liquibase.org/xml/ns/dbchangelog"
    xmlns:xsi="http://www.w3.org/2001/XMLSchema-instance"
    xmlns:mongodb="http://www.liquibase.org/xml/ns/mongodb"
    xsi:schemaLocation="http://www.liquibase.org/xml/ns/dbchangelog
    http://www.liquibase.org/xml/ns/dbchangelog/dbchangelog-latest.xsd
    http://www.liquibase.org/xml/ns/mongodb
    http://www.liquibase.org/xml/ns/mongodb/liquibase-mongodb-latest.xsd">

    <changeSet id="1" author="x">
        <preConditions onFail="CONTINUE">
            <mongodb:collectionExists collectionName="test" />
        </preConditions>
        <mongodb:runCommand>
            <mongodb:command>
                <![CDATA[
                    {
                      renameCollection: "test",
                      updates: "test2"
                    }
                 ]]>
            </mongodb:command>
        </mongodb:runCommand>
    </changeSet>

</databaseChangeLog>
